{
    "name": "DefinitionObject",
    "fields": [
        {
            "fieldName": "name",
            "fieldType": "String",
            "fieldValidateRules": [
                "required"
            ]
        },
        {
            "fieldName": "parserName",
            "fieldType": "String",
            "fieldValidateRules": [
                "required"
            ]
        },
        {
            "fieldName": "isActive",
            "fieldType": "Boolean"
        },
        {
            "fieldName": "createdAt",
            "fieldType": "Instant",
            "fieldValidateRules": [
                "required"
            ]
        },
        {
            "fieldName": "updatedAt",
            "fieldType": "Instant"
        }
    ],
    "relationships": [
        {
            "relationshipType": "one-to-one",
            "otherEntityName": "goal",
            "otherEntityRelationshipName": "definitionObject",
            "relationshipName": "goal",
            "otherEntityField": "id",
            "ownerSide": true
        }
    ],
    "changelogDate": "20200206185543",
    "entityTableName": "definition_object",
    "dto": "mapstruct",
    "pagination": "no",
    "service": "serviceClass",
    "jpaMetamodelFiltering": false,
    "fluentMethods": true,
    "readOnly": false,
    "clientRootFolder": "",
    "applications": [
        "myMonolith"
    ]
}